tests/__init__.py
tests/test_module1.py
tests/test_module2.py
climalysis-0.2.0.dist-info/LICENSE
climalysis-0.2.0.dist-info/METADATA
climalysis-0.2.0.dist-info/WHEEL
climalysis-0.2.0.dist-info/top_level.txt
climalysis-0.2.0.dist-info/RECORD
