Metadata-Version: 2.1
Name: climalysis
Version: 0.2.0
Summary: A comprehensive toolkit for climate impact analysis.
Author: Jake Casselman
Author-email: <jake.casselman@climalinks.com
Keywords: python,climate,analysis,climate analysis,climate data,impact analysis
Classifier: Development Status :: 3 - Alpha
Classifier: Intended Audience :: Science/Research
Classifier: Programming Language :: Python :: 3
Classifier: Operating System :: OS Independent
Classifier: Topic :: Scientific/Engineering :: Atmospheric Science
License-File: LICENSE
Requires-Dist: numpy
Requires-Dist: pandas
Requires-Dist: matplotlib
